<?xml version="1.0" encoding="utf-8" ?>
<LanguageData>

  <StatsReport_BaseValue>Базовое значение</StatsReport_BaseValue>
  <StatsReport_RelevantTraits>Влияющие черты</StatsReport_RelevantTraits>
  <StatsReport_RelevantGear>Влияющие вещи</StatsReport_RelevantGear>
  <StatsReport_Material>Материал</StatsReport_Material>
  <StatsReport_CharacterQuality>Черты характера</StatsReport_CharacterQuality>
  <StatsReport_Skills>Факторы навыков</StatsReport_Skills>
  <StatsReport_OtherStats>Другие факторы</StatsReport_OtherStats>
  <StatsReport_HealthFactors>Факторы здоровья</StatsReport_HealthFactors>
  <HealthFactorPercentImpact>влияет на {0}</HealthFactorPercentImpact>
  <StatsReport_PostProcessed>Пост-обработка кривыми</StatsReport_PostProcessed>
  <StatsReport_FinalValue>Итого</StatsReport_FinalValue>
  <StatsReport_MarketValueFromStuffsAndWork>Базовая рыночная стоимость рассчитана из материалов и количества работы.</StatsReport_MarketValueFromStuffsAndWork>
  <StatsReport_QualityMultiplier>Множитель качества</StatsReport_QualityMultiplier>
  <StatsReport_AgeMultiplier>Множитель возраста {0}</StatsReport_AgeMultiplier>
  <StatsReport_HealthMultiplier>Множитель здоровья {0}</StatsReport_HealthMultiplier>
  <StatsReport_MoodMultiplier>Множитель настроения {0}</StatsReport_MoodMultiplier>
  <StatsReport_InBed>В кровати</StatsReport_InBed>

</LanguageData>
