<?xml version="1.0" encoding="UTF-8"?>
<LanguageData>
  
  <!-- EN: fine burgundy carpet -->
  <CarpetFineBurgundy.label>красивый багровый ковёр</CarpetFineBurgundy.label>
  <!-- EN: Classic burgundy carpet for that classic rich look. -->
  <CarpetFineBurgundy.description>Классический багровый ковёр для создания классической обстановки роскоши</CarpetFineBurgundy.description>
  
  <!-- EN: fine indigo carpet -->
  <CarpetFineIndigo.label>красивый аметистовый ковёр</CarpetFineIndigo.label>
  <!-- EN: Soft and silky indigo carpet, for that extra sense of pomp. -->
  <CarpetFineIndigo.description>Мягкий и шелковистый аметистовый ковёр, добавляющий чувства пышности обстановке</CarpetFineIndigo.description>
  
  <!-- EN: fine white carpet -->
  <CarpetFineWhite.label>красивый белый ковёр</CarpetFineWhite.label>
  <!-- EN: Sublime white carpet, glimmering with subtle patterns. -->
  <CarpetFineWhite.description>Ковёр благородного белого цвета, сияющий едва заметными узорами</CarpetFineWhite.description>
  
</LanguageData>