<?xml version="1.0" encoding="utf-8" ?>
<LanguageData>

	
	<AnimalChat.label>общение с животным</AnimalChat.label>
	<!-- Надо это? Не пойму.-->
<!--
  <logRulesInitiator>
      <rulesStrings>
        <li>logentry->Communicated with [other_nameShortIndef], attempting to build rapport.</li>
      </rulesStrings>
    </logRulesInitiator>
    <logRulesRecipient>
      <rulesStrings>
        <li>logentry->Responded to [other_nameShortIndef]'s friendly communication.</li>
      </rulesStrings>
    </logRulesRecipient>
  </InteractionDef>
-->

    <TrainAttempt.label>попытка натренировать</TrainAttempt.label>
<!--
    <logRulesInitiator>
      <rulesStrings>
        <li>logentry->Trained [other_nameShortIndef].</li>
      </rulesStrings>
    </logRulesInitiator>
    <logRulesRecipient>
      <rulesStrings>
        <li>logentry->Was trained by [other_nameShortIndef].</li>
      </rulesStrings>
    </logRulesRecipient>
  </InteractionDef>
--> 

	<TameAttempt.label>попытка приручить</TameAttempt.label>
<!--
    <logRulesInitiator>
      <rulesStrings>
        <li>logentry->Attempted to tame [other_nameShortIndef].</li>
      </rulesStrings>
    </logRulesInitiator>
    <logRulesRecipient>
      <rulesStrings>
        <li>logentry->Watches [other_nameShortIndef] attempt to tame me.</li>
      </rulesStrings>
    </logRulesRecipient>
  </InteractionDef>
-->

</LanguageData>