<?xml version="1.0" encoding="utf-8" ?>
<LanguageData>

  <!-- External violence -->

	<Crush.deathMessage>{0} был раздавлен насметрь.</Crush.deathMessage>
  
	<Bludgeon.deathMessage>{0} был забит досмерти.</Bludgeon.deathMessage>

	<Bullet.deathMessage>{0} был застрелен.</Bullet.deathMessage>

	<Bomb.deathMessage>{0} был убит в результате взрыва.</Bomb.deathMessage>

	<Flame.deathMessage>{0} сгорел.</Flame.deathMessage>

	<Stun.deathMessage>{0} был оглушен и убит.</Stun.deathMessage>
  
  
  
  <!-- etc -->
  
	<Bleeding.deathMessage>{0} умер от кровопотери.</Bleeding.deathMessage>
	
	<Suffocation.deathMessage>{0} задохнулся.</Suffocation.deathMessage>
	
	<Starvation.deathMessage>{0} умер от голода.</Starvation.deathMessage>
	
	
	
	
	
	
	
	
	
</LanguageData>