<?xml version="1.0" encoding="UTF-8"?>
<LanguageData>
  
  <!-- EN: caves -->
  <Caves.label>TODO</Caves.label>
  <!-- EN: Small cave networks can be found within the rocks. -->
  <Caves.description>TODO</Caves.description>
  
  <!-- EN: coast -->
  <Coast.label>TODO</Coast.label>
  <!-- EN: This tile borders the coast. -->
  <Coast.description>TODO</Coast.description>
  
  <!-- EN: mountain -->
  <Mountain.label>TODO</Mountain.label>
  <!-- EN: A mountain fills one side of this tile. -->
  <Mountain.description>TODO</Mountain.description>
  
  <!-- EN: river -->
  <River.label>TODO</River.label>
  <!-- EN: A stream of fresh water flows through here. -->
  <River.description>TODO</River.description>
  
  <!-- EN: underground cave -->
  <UndergroundCave.label>TODO</UndergroundCave.label>
  
</LanguageData>