<?xml version="1.0" encoding="utf-8" ?>
<LanguageData>
 
        <Research.pawnLabel>Ученый</Research.pawnLabel>
        <Research.gerundLabel>Исследования</Research.gerundLabel>
        <Research.tooltipDesc>Researchers do research work.</Research.tooltipDesc>
		<Research.verb>Research at</Research.verb>	
       
        <Cleaning.pawnLabel>Уборщик</Cleaning.pawnLabel>
        <Cleaning.gerundLabel>Уборка</Cleaning.gerundLabel>
		<Cleaning.tooltipDesc>Cleaners wipe up spills and sweep up debris in designated home zones, making the colony more enjoyable to live in.</Cleaning.tooltipDesc>
		<Cleaning.verb>Clean</Cleaning.verb>
       
        <Hauling.pawnLabel>Носильщик</Hauling.pawnLabel>
        <Hauling.gerundLabel>Перенос</Hauling.gerundLabel>
		<Hauling.tooltipDesc>Haulers carry things to where they need to be.</Hauling.tooltipDesc>
		<Hauling.verb>Haul</Hauling.verb>
       
        <Art.pawnLabel>Артист</Art.pawnLabel>
        <Art.gerundLabel>Искусство</Art.gerundLabel>
        <Art.tooltipDesc>Artists create beautiful works of art.</Art.tooltipDesc>
        <Art.verb>Do art at</Art.verb>
       
        <Crafting.pawnLabel>Crafter</Crafting.pawnLabel>
        <Crafting.gerundLabel>Ремесло</Crafting.gerundLabel>
		<Crafting.tooltipDesc>Crafters create things from rough materials.</Crafting.tooltipDesc>
		<Crafting.verb>Craft at</Crafting.verb>
       
        <PlantCutting.pawnLabel>Plant cutter</PlantCutting.pawnLabel>
        <PlantCutting.gerundLabel>Садоводство</PlantCutting.gerundLabel>
		<PlantCutting.tooltipDesc>Plant cutters remove and harvest the wild plants you've designated.</PlantCutting.tooltipDesc>
		<PlantCutting.verb>Cut</PlantCutting.verb>

        <Mining.pawnLabel>Шахтер</Mining.pawnLabel>
        <Mining.gerundLabel>Горное дело</Mining.gerundLabel>
		<Mining.tooltipDesc>Miners dig out squares that you have designated for mining. If these are mineral squares, they will yield usable minerals.</Mining.tooltipDesc>
		<Mining.verb>Mine</Mining.verb>
   
        <Growing.pawnLabel>Фермер</Growing.pawnLabel>
        <Growing.gerundLabel>Фермерство</Growing.gerundLabel>
		<Growing.tooltipDesc>Growers plant seeds and harvest grown crops.</Growing.tooltipDesc>
		<Growing.verb>Grow</Growing.verb>     
       
        <Repair.pawnLabel>Мастер</Repair.pawnLabel>
        <Repair.gerundLabel>Ремонт</Repair.gerundLabel>
		<Repair.tooltipDesc>Repairers fix broken-down buildings and equipment.</Repair.tooltipDesc>
		<Repair.verb>Repair</Repair.verb>
 
        <Construction.pawnLabel>Строитель</Construction.pawnLabel>
        <Construction.gerundLabel>Строительство</Construction.gerundLabel>
		<Construction.tooltipDesc>Constructors build things that you've designated.</Construction.tooltipDesc>
		<Construction.verb>Construct</Construction.verb>	
       
        <Hunting.pawnLabel>Охотник</Hunting.pawnLabel>
        <Hunting.gerundLabel>Охота</Hunting.gerundLabel>
		<Hunting.tooltipDesc>Hunters kill animals which are designated to be hunted.</Hunting.tooltipDesc>
		<Hunting.verb>Hunt</Hunting.verb>
 
        <Cooking.pawnLabel>Кок</Cooking.pawnLabel>
        <Cooking.gerundLabel>Кулинария</Cooking.gerundLabel>
		<Cooking.tooltipDesc>Cooks fill paste dispensers and prepare meals.</Cooking.tooltipDesc>
		<Cooking.verb>Cook</Cooking.verb>
 
        <Warden.pawnLabel>Сторож</Warden.pawnLabel>
		<Warden.gerundLabel>Надсмотр</Warden.gerundLabel>
		<Warden.tooltipDesc>Wardens visit prisoners to recruit them, have a nice chat, beat them, or execute them - whatever you have decided. Wardens also deliver food to prisoners.</Warden.tooltipDesc>
		<Warden.verb>Handle</Warden.verb>

        <Doctor.pawnLabel>Доктор</Doctor.pawnLabel>
        <Doctor.gerundLabel>Медицина</Doctor.gerundLabel>
		<Doctor.tooltipDesc>Doctors bring food those lying incapacitated in bed. They will care for both colonists and prisoners.</Doctor.tooltipDesc>
		<Doctor.verb>Care for</Doctor.verb>
       
        <Firefighter.pawnLabel>Пожарник</Firefighter.pawnLabel>
        <Firefighter.gerundLabel>Пожаротушение</Firefighter.gerundLabel>
		<Firefighter.tooltipDesc>Firefighters extinguish fires in the colony.</Firefighter.tooltipDesc>
		<Firefighter.verb>Extinguish</Firefighter.verb>
 
</LanguageData>