<?xml version="1.0" encoding="utf-8" ?>
<LanguageData>

	<SpeedOffset.degreeDatas.slowpoke.label>медлительность</SpeedOffset.degreeDatas.slowpoke.label>
	<SpeedOffset.degreeDatas.slowpoke.description>[PAWN_nameDef] всегда плетётся позади группы, когда и куда бы она не шла.</SpeedOffset.degreeDatas.slowpoke.description>
	<SpeedOffset.degreeDatas.fast_walker.label>скороход</SpeedOffset.degreeDatas.fast_walker.label>
	<SpeedOffset.degreeDatas.fast_walker.description>[PAWN_nameDef] любит ходить пешком. [PAWN_pronoun] ходит быстрее, чем большинство людей.</SpeedOffset.degreeDatas.fast_walker.description>
	<SpeedOffset.degreeDatas.jogger.label>бегун</SpeedOffset.degreeDatas.jogger.label>
	<SpeedOffset.degreeDatas.jogger.description>[PAWN_nameDef] всегда спешит. Да так сильно, что остальные угнаться не могут.</SpeedOffset.degreeDatas.jogger.description>

	<DrugDesire.degreeDatas.chemical_fascination.label>страсть к «химии»</DrugDesire.degreeDatas.chemical_fascination.label>
	<DrugDesire.degreeDatas.chemical_fascination.description>[PAWN_nameDef] имеет сильную тягу к химическим источникам удовольствия, в том числе к тяжелым наркотикам. [PAWN_pronoun] употребляет их значительно больше и чаще других, временами устраивая затяжные наркотические марафоны. [PAWN_nameDef] не обращает внимания на указания не трогать «химию».</DrugDesire.degreeDatas.chemical_fascination.description>
	<DrugDesire.degreeDatas.chemical_interest.label>интерес к «химии»</DrugDesire.degreeDatas.chemical_interest.label>
	<DrugDesire.degreeDatas.chemical_interest.description>[PAWN_nameDef] любит выпить, имеет слабость к лёгким наркотикам и другим химическим источникам удовольствия. [PAWN_pronoun] употребляет их больше и чаще других, иногда устраивая загулы. [PAWN_nameDef] не обращает внимания на указания не трогать «химию».</DrugDesire.degreeDatas.chemical_interest.description>
	<DrugDesire.degreeDatas.teetotaler.label>трезвенник</DrugDesire.degreeDatas.teetotaler.label>
	<DrugDesire.degreeDatas.teetotaler.description>[PAWN_nameDef] не приемлет идею получения удовольствия от «химии» и держится подальше от алкоголя и наркотиков.</DrugDesire.degreeDatas.teetotaler.description>

	<NaturalMood.degreeDatas.sanguine.label>сангвиник</NaturalMood.degreeDatas.sanguine.label>
	<NaturalMood.degreeDatas.sanguine.description>[PAWN_nameDef] всегда в приподнятом настроении, что бы ни происходило вокруг.</NaturalMood.degreeDatas.sanguine.description>
	<NaturalMood.degreeDatas.optimist.label>оптимист</NaturalMood.degreeDatas.optimist.label>
	<NaturalMood.degreeDatas.optimist.description>[PAWN_nameDef] оптимист от природы. [PAWN_objective] сложно испортить настроение.</NaturalMood.degreeDatas.optimist.description>
	<NaturalMood.degreeDatas.pessimist.label>пессимист</NaturalMood.degreeDatas.pessimist.label>
	<NaturalMood.degreeDatas.pessimist.description>[PAWN_nameDef] видит жизнь только с плохой стороны.</NaturalMood.degreeDatas.pessimist.description>
	<NaturalMood.degreeDatas.depressive.label>подавленность</NaturalMood.degreeDatas.depressive.label>
	<NaturalMood.degreeDatas.depressive.description>[PAWN_nameDef] всегда в плохом настроении. И оно редко улучшается, даже когда всё хорошо.</NaturalMood.degreeDatas.depressive.description>

	<Nerves.degreeDatas.ironwilled.label>железные нервы</Nerves.degreeDatas.ironwilled.label>
	<Nerves.degreeDatas.ironwilled.description>Воля [PAWN_nameDef] как железный щит. [PAWN_pronoun] продолжает идти в огонь и воду, когда остальные давно сдались.</Nerves.degreeDatas.ironwilled.description>
	<Nerves.degreeDatas.steadfast.label>уравновешенность</Nerves.degreeDatas.steadfast.label>
	<Nerves.degreeDatas.steadfast.description>[PAWN_nameDef] обладает психической устойчивостью к стрессам, которых большинство не выдерживает.</Nerves.degreeDatas.steadfast.description>
	<Nerves.degreeDatas.nervous.label>неуравновешенность</Nerves.degreeDatas.nervous.label>
	<Nerves.degreeDatas.nervous.description>[PAWN_nameDef] может сорваться при сильном эмоциональном напряжений.</Nerves.degreeDatas.nervous.description>
	<Nerves.degreeDatas.volatile.label>слабые нервы</Nerves.degreeDatas.volatile.label>
	<Nerves.degreeDatas.volatile.description>[PAWN_nameDef] всегда на взводе. Малейшее эмоциональное напряжение может закончиться нервным срывом.</Nerves.degreeDatas.volatile.description>

	<Neurotic.degreeDatas.neurotic.label>лёгкая неврастения</Neurotic.degreeDatas.neurotic.label>
	<Neurotic.degreeDatas.neurotic.description>[PAWN_nameDef] любит всё делать правильно, отчего работает больше и усерднее остальных. Такое напряжение иногда приводит к нервными срывам.</Neurotic.degreeDatas.neurotic.description>
	<Neurotic.degreeDatas.very_neurotic.label>тяжёлая неврастения</Neurotic.degreeDatas.very_neurotic.label>
	<Neurotic.degreeDatas.very_neurotic.description>Постоянные переживания о качестве своей работы заставляют [PAWN_nameDef] выполнять её идеально, что приводит к частым нервным расстройствам.</Neurotic.degreeDatas.very_neurotic.description>

	<Industriousness.degreeDatas.industrious.label>усердие</Industriousness.degreeDatas.industrious.label>
	<Industriousness.degreeDatas.industrious.description>[PAWN_nameDef] легко концентрируется на работе и выполняет задачи гораздо быстрее обычных людей.</Industriousness.degreeDatas.industrious.description>
	<Industriousness.degreeDatas.hard_worker.label>трудолюбие</Industriousness.degreeDatas.hard_worker.label>
	<Industriousness.degreeDatas.hard_worker.description>Обладая природным трудолюбием, [PAWN_nameDef] выполняет работу быстрее остальных.</Industriousness.degreeDatas.hard_worker.description>
	<Industriousness.degreeDatas.lazy.label>леность</Industriousness.degreeDatas.lazy.label>
	<Industriousness.degreeDatas.lazy.description>[PAWN_nameDef] иногда ленится.</Industriousness.degreeDatas.lazy.description>
	<Industriousness.degreeDatas.slothful.label>праздность</Industriousness.degreeDatas.slothful.label>
	<Industriousness.degreeDatas.slothful.description>[PAWN_nameDef] любит бездельничать и ненавидит работать. [PAWN_pronoun] двигается медленно и редко концентрируется на задаче.</Industriousness.degreeDatas.slothful.description>

	<PsychicSensitivity.degreeDatas.psychically_hypersensitive.label>гиперчувствительность</PsychicSensitivity.degreeDatas.psychically_hypersensitive.label>
	<PsychicSensitivity.degreeDatas.psychically_hypersensitive.description>Разум [PAWN_nameDef] отзывчив, словно тонко настроенный музыкальный инструмент. [PAWN_pronoun] чрезвычайно чувствителен(а) к психическим воздействиям.</PsychicSensitivity.degreeDatas.psychically_hypersensitive.description>
	<PsychicSensitivity.degreeDatas.psychically_sensitive.label>восприимчивость</PsychicSensitivity.degreeDatas.psychically_sensitive.label>
	<PsychicSensitivity.degreeDatas.psychically_sensitive.description>Разум [PAWN_nameDef] чувствителен к психическим воздействиям.</PsychicSensitivity.degreeDatas.psychically_sensitive.description>
	<PsychicSensitivity.degreeDatas.psychically_dull.label>психическая вялость</PsychicSensitivity.degreeDatas.psychically_dull.label>
	<PsychicSensitivity.degreeDatas.psychically_dull.description>[PAWN_nameDef] — психически устойчивая личность, которую мало что способно потревожить.</PsychicSensitivity.degreeDatas.psychically_dull.description>
	<PsychicSensitivity.degreeDatas.psychically_deaf.label>психическая глухота</PsychicSensitivity.degreeDatas.psychically_deaf.label>
	<PsychicSensitivity.degreeDatas.psychically_deaf.description>Разум [PAWN_nameDef] работает на волне, отличной от всех остальных. [PAWN_pronoun] не подвергается влиянию психических воздействий.</PsychicSensitivity.degreeDatas.psychically_deaf.description>

	<ShootingAccuracy.degreeDatas.careful_shooter.label>аккуратный стрелок</ShootingAccuracy.degreeDatas.careful_shooter.label>
	<ShootingAccuracy.degreeDatas.careful_shooter.description>[PAWN_nameDef] чаще других попадает в цель, но [PAWN_objective] нужно время, чтобы как следует прицелиться.</ShootingAccuracy.degreeDatas.careful_shooter.description>
	<ShootingAccuracy.degreeDatas.triggerhappy.label>беспечный стрелок</ShootingAccuracy.degreeDatas.triggerhappy.label>
	<ShootingAccuracy.degreeDatas.triggerhappy.description>Пиу-пиу-пиу! [PAWN_nameDef] обожает жать на курок. Точность при этом страдает, но [PAWN_possessive] это не заботит, потому что пушки — это здорово!</ShootingAccuracy.degreeDatas.triggerhappy.description>

	<Beauty.degreeDatas.beautiful.label>невероятная красота</Beauty.degreeDatas.beautiful.label>
	<Beauty.degreeDatas.beautiful.description>[PAWN_nameDef] обладает исключительной красотой. [PAWN_possessive] лицо имеет несколько экзотичные, но в то же время крайне привлекательные черты, а взгляд буквально очаровывает. Люди тянутся к [PAWN_nameDef] ещё до того, как [PAWN_pronoun] что-нибудь произнесёт.</Beauty.degreeDatas.beautiful.description>
	<Beauty.degreeDatas.pretty.label>красота</Beauty.degreeDatas.pretty.label>
	<Beauty.degreeDatas.pretty.description>У [PAWN_nameDef] миловидное личико, вызывающее у людей симпатию.</Beauty.degreeDatas.pretty.description>
	<Beauty.degreeDatas.ugly.label>уродство</Beauty.degreeDatas.ugly.label>
	<Beauty.degreeDatas.ugly.description>[PAWN_nameDef] имеет непривлекательную, отталкивающую внешность.</Beauty.degreeDatas.ugly.description>
	<Beauty.degreeDatas.staggeringly_ugly.label>невероятное уродство</Beauty.degreeDatas.staggeringly_ugly.label>
	<Beauty.degreeDatas.staggeringly_ugly.description>[PAWN_nameDef] обладает поистине безобразной внешностью. [PAWN_possessive] лицо — что-то среднее между рисунком бездарного ребёнка, заспиртованным в банке уродцем и произведением современного искусства. Людям приходится прикладывать усилие, чтобы просто смотреть [PAWN_objective] в лицо при разговоре.</Beauty.degreeDatas.staggeringly_ugly.description>

	<Immunity.degreeDatas.superimmune.label>сильный иммунитет</Immunity.degreeDatas.superimmune.label>
	<Immunity.degreeDatas.superimmune.description>[PAWN_nameDef] от природы обладает стойкой иммунной системой. Скорость, с которой у н[PAWN_possessive] вырабатывается иммунитет к различным возбудителям, гораздо выше, чем у остальных. [PAWN_pronoun] справится с болезнью, которая обычного человека может просто убить.</Immunity.degreeDatas.superimmune.description>
	<Immunity.degreeDatas.sickly.label>слабый иммунитет</Immunity.degreeDatas.sickly.label>
	<Immunity.degreeDatas.sickly.description>[PAWN_nameDef] имеет слабую иммунную систему. [PAWN_pronoun] болеет гораздо чаще остальных. Зачастую у н[PAWN_possessive] возникают недуги, от которых не страдает больше никто в поселении.</Immunity.degreeDatas.sickly.description>

</LanguageData>
