<?xml version="1.0" encoding="utf-8" ?>
<LanguageData>

	<ButcherCorpseFlesh.label>разделать тушу</ButcherCorpseFlesh.label>
	<ButcherCorpseFlesh.description>Разделать тушу, чтобы получить мясо.</ButcherCorpseFlesh.description>
	<ButcherCorpseFlesh.jobString>Разделывает.</ButcherCorpseFlesh.jobString>

	<ButcherCorpseMechanoid.label>разобрать механоида</ButcherCorpseMechanoid.label>
	<ButcherCorpseMechanoid.description>Разобрать механоида на составные части.</ButcherCorpseMechanoid.description>
	<ButcherCorpseMechanoid.jobString>Разбирает механоида.</ButcherCorpseMechanoid.jobString>

	<!-- 20 + 20 ingredients yield 50 kibble -->
	
	<MakeKibble.label>комбикорм</MakeKibble.label>
    <MakeKibble.description>Сделать пищу для животных из сырого мяса и растений.</MakeKibble.description>
    <MakeKibble.jobString>Делает комбикорм.</MakeKibble.jobString>

	</LanguageData>