<?xml version="1.0" encoding="utf-8" ?>
<LanguageData>
	
	<Orders.label>Действия</Orders.label>
    <Orders.description>Выбор действий для конкретных вещей.</Orders.description>
	
	<Zone.label>Зоны</Zone.label>
    <Zone.description>Выбор зон для определенных видов работ.</Zone.description>
	
	<Structure.label>Структуры</Structure.label>
    <Structure.description>Строительные конструкции, такие как стены и проводка.</Structure.description>
	
	<Production.label>Производство</Production.label>
    <Production.description>Структуры, которые необходимы для производства.</Production.description>
	
	<Furniture.label>Мебель</Furniture.label>
    <Furniture.description>Мелкие постройки.</Furniture.description>
	
	<Power.label>Электро</Power.label>
    <Power.description>Производство электроэнергии, передача и управление.</Power.description>
	
	<Security.label>Оборона</Security.label>
    <Security.description>Безопасность и боевые ориентированные конструкции.</Security.description>
	
	<Misc.label>Разное</Misc.label>
    <Misc.description>Различные структуры.</Misc.description>
	
	<Floors.label>Покрытие</Floors.label>
    <Floors.description>Полы.</Floors.description>
	
	<Decoration.label>Дикорации</Decoration.label>
    <Decoration.description>Вещи, которые влияют на благополучие колонистов.</Decoration.description>

</LanguageData>